necessary/__init__.py
necessary/__init__.pyi
necessary/core.py
necessary/core.pyi
necessary/py.typed
necessary-0.4.3.dist-info/LICENSE
necessary-0.4.3.dist-info/METADATA
necessary-0.4.3.dist-info/WHEEL
necessary-0.4.3.dist-info/top_level.txt
necessary-0.4.3.dist-info/RECORD
