Metadata-Version: 2.1
Name: necessary
Version: 0.4.3
Summary: Python package to enforce optional dependencies
Author-email: Luca Soldaini <luca@soldaini.net>
License: Apache-2.0
Project-URL: Homepage, https://github.com/soldni/necessary
Project-URL: Source, https://github.com/soldni/necessary
Project-URL: Tracker, https://github.com/soldni/necessary/issues
Classifier: Development Status :: 5 - Production/Stable
Classifier: License :: OSI Approved :: Apache Software License
Classifier: Operating System :: OS Independent
Classifier: Programming Language :: Python :: 3
Classifier: Topic :: Software Development :: Libraries :: Python Modules
Classifier: Topic :: Utilities
Classifier: Typing :: Typed
Requires-Python: >=3.8
Provides-Extra: dev
License-File: LICENSE
